_scrypt.cpython-38-darwin.so
pyscryptfirebase/__init__.py
pyscryptfirebase/pyscryptfirebase.py
pyscryptfirebase-0.0.2.dist-info/LICENSE
pyscryptfirebase-0.0.2.dist-info/METADATA
pyscryptfirebase-0.0.2.dist-info/WHEEL
pyscryptfirebase-0.0.2.dist-info/top_level.txt
pyscryptfirebase-0.0.2.dist-info/RECORD
