Metadata-Version: 2.1
Name: pyscryptfirebase
Version: 0.0.2
Summary: Python wrapper for the Firebase scrypt password hashing utility
Home-page: https://github.com/mcsimps2/py-scrypt-firebase/
Author: Matt Simpson
Author-email: mcsimps2@gmail.com
License: 2-clause BSD
Platform: UNKNOWN
Classifier: Intended Audience :: Developers
Classifier: License :: OSI Approved :: BSD License
Classifier: Programming Language :: Python :: 2.7
Classifier: Programming Language :: Python :: 3
Classifier: Programming Language :: Python :: 3.4
Classifier: Programming Language :: Python :: 3.5
Classifier: Programming Language :: Python :: 3.6
Classifier: Programming Language :: Python :: 3.7
Classifier: Topic :: Security :: Cryptography
Classifier: Topic :: Software Development :: Libraries
Classifier: Operating System :: OS Independent
